dask/__init__.py
dask/__main__.py
dask/_collections.py
dask/_compatibility.py
dask/_dispatch.py
dask/_expr.py
dask/_pandas_compat.py
dask/_task_spec.py
dask/_version.py
dask/backends.py
dask/base.py
dask/blockwise.py
dask/cache.py
dask/callbacks.py
dask/cli.py
dask/config.py
dask/conftest.py
dask/context.py
dask/core.py
dask/dask-schema.yaml
dask/dask.yaml
dask/datasets.py
dask/delayed.py
dask/distributed.py
dask/dot.py
dask/graph_manipulation.py
dask/hashing.py
dask/highlevelgraph.py
dask/layers.py
dask/local.py
dask/ml.py
dask/multiprocessing.py
dask/optimization.py
dask/order.py
dask/py.typed
dask/rewrite.py
dask/sizeof.py
dask/system.py
dask/task_spec.py
dask/threaded.py
dask/tokenize.py
dask/typing.py
dask/utils.py
dask/utils_test.py
dask/array/NUMPY_LICENSE.txt
dask/array/__init__.py
dask/array/_reductions_generic.py
dask/array/_shuffle.py
dask/array/api.py
dask/array/backends.py
dask/array/blockwise.py
dask/array/chunk.py
dask/array/chunk_types.py
dask/array/core.py
dask/array/creation.py
dask/array/cupy_entry_point.py
dask/array/dispatch.py
dask/array/einsumfuncs.py
dask/array/fft.py
dask/array/gufunc.py
dask/array/image.py
dask/array/linalg.py
dask/array/ma.py
dask/array/numpy_compat.py
dask/array/optimization.py
dask/array/overlap.py
dask/array/percentile.py
dask/array/random.py
dask/array/rechunk.py
dask/array/reductions.py
dask/array/reshape.py
dask/array/routines.py
dask/array/slicing.py
dask/array/stats.py
dask/array/svg.py
dask/array/tiledb_io.py
dask/array/ufunc.py
dask/array/utils.py
dask/array/wrap.py
dask/array/_array_expr/__init__.py
dask/array/_array_expr/_backends.py
dask/array/_array_expr/_blockwise.py
dask/array/_array_expr/_collection.py
dask/array/_array_expr/_creation.py
dask/array/_array_expr/_expr.py
dask/array/_array_expr/_gufunc.py
dask/array/_array_expr/_io.py
dask/array/_array_expr/_map_blocks.py
dask/array/_array_expr/_overlap.py
dask/array/_array_expr/_rechunk.py
dask/array/_array_expr/_reductions.py
dask-2025.9.2.dist-info/licenses/LICENSE.txt
dask-2025.9.2.dist-info/licenses/dask/array/NUMPY_LICENSE.txt
dask-2025.9.2.dist-info/METADATA
dask-2025.9.2.dist-info/WHEEL
dask-2025.9.2.dist-info/entry_points.txt
dask-2025.9.2.dist-info/top_level.txt
dask-2025.9.2.dist-info/RECORD
