Metadata-Version: 2.4
Name: dask
Version: 2025.9.2
Summary: Parallel PyData with Task Scheduling
Maintainer-email: Matthew Rocklin <mrocklin@gmail.com>
License: BSD-3-Clause
Project-URL: Homepage, https://github.com/dask/dask/
Keywords: task-scheduling parallel numpy pandas pydata
Classifier: Development Status :: 5 - Production/Stable
Classifier: Intended Audience :: Developers
Classifier: Intended Audience :: Science/Research
Classifier: License :: OSI Approved :: BSD License
Classifier: Operating System :: OS Independent
Classifier: Programming Language :: Python
Classifier: Programming Language :: Python :: 3
Classifier: Programming Language :: Python :: 3 :: Only
Classifier: Programming Language :: Python :: 3.10
Classifier: Programming Language :: Python :: 3.11
Classifier: Programming Language :: Python :: 3.12
Classifier: Programming Language :: Python :: 3.13
Classifier: Topic :: Scientific/Engineering
Classifier: Topic :: System :: Distributed Computing
Requires-Python: >=3.10
License-File: LICENSE.txt
License-File: dask/array/NUMPY_LICENSE.txt
Requires-Dist: click>=8.1
Requires-Dist: cloudpickle>=3.0.0
Requires-Dist: fsspec>=2021.09.0
Requires-Dist: packaging>=20.0
Requires-Dist: partd>=1.4.0
Requires-Dist: pyyaml>=5.3.1
Requires-Dist: toolz>=0.10.0
Requires-Dist: importlib_metadata>=4.13.0; python_version < "3.12"
Provides-Extra: array
Requires-Dist: numpy>=1.24; extra == "array"
Provides-Extra: bag
Provides-Extra: dataframe
Requires-Dist: dask[array]; extra == "dataframe"
Requires-Dist: pandas>=2.0; extra == "dataframe"
Requires-Dist: pyarrow>=14.0.1; extra == "dataframe"
Provides-Extra: distributed
Requires-Dist: distributed==2025.9.2; extra == "distributed"
Provides-Extra: diagnostics
Requires-Dist: bokeh>=3.1.0; extra == "diagnostics"
Requires-Dist: jinja2>=2.10.3; extra == "diagnostics"
Provides-Extra: delayed
Provides-Extra: complete
Requires-Dist: dask[array,dataframe,diagnostics,distributed]; extra == "complete"
Requires-Dist: pyarrow>=14.0.1; extra == "complete"
Requires-Dist: lz4>=4.3.2; extra == "complete"
Provides-Extra: test
Requires-Dist: pandas[test]; extra == "test"
Requires-Dist: pytest; extra == "test"
Requires-Dist: pytest-cov; extra == "test"
Requires-Dist: pytest-mock; extra == "test"
Requires-Dist: pytest-rerunfailures; extra == "test"
Requires-Dist: pytest-timeout; extra == "test"
Requires-Dist: pytest-xdist; extra == "test"
Requires-Dist: pre-commit; extra == "test"
Dynamic: license-file
